yapbol/__init__.py
yapbol/pbo.py
yapbol-0.2.dist-info/licenses/LICENSE
yapbol-0.2.dist-info/METADATA
yapbol-0.2.dist-info/WHEEL
yapbol-0.2.dist-info/top_level.txt
yapbol-0.2.dist-info/RECORD
