Metadata-Version: 2.4
Name: yapbol
Version: 0.2
Summary: Yet Another PBO Library
Author: Lukasz Taczuk
License-Expression: GPL-3.0-only
Project-URL: Homepage, https://github.com/overfl0/yapbol
Project-URL: Repository, https://github.com/overfl0/yapbol
Keywords: arma,pbo
Classifier: Development Status :: 3 - Alpha
Classifier: Intended Audience :: Developers
Classifier: Topic :: Software Development :: Build Tools
Classifier: Programming Language :: Python :: 3
Classifier: Programming Language :: Python :: 3.8
Classifier: Programming Language :: Python :: 3.9
Classifier: Programming Language :: Python :: 3.10
Classifier: Programming Language :: Python :: 3.11
Classifier: Programming Language :: Python :: 3.12
Classifier: Programming Language :: Python :: 3.13
Requires-Python: >=3.8
License-File: LICENSE
Dynamic: license-file
